<annotation>
    <folder>VOC2007</folder>
    <filename>00000552.jpg</filename>
    <source>
        <database>My Database</database>
        <annotation>VOC2007</annotation>
        <image>flickr</image>
        <flickrid>NULL</flickrid>
    </source>
    <owner>
        <flickrid>NULL</flickrid>
        <name>LK</name>
    </owner>
    <size>
        <width>1083</width>
        <height>923</height>
        <depth>3</depth>
    </size>
    <segmented>0</segmented>
    <object>
        <name>oiltank</name>
        <pose>Unspecified</pose>
        <truncated>0</truncated>
        <difficult>0</difficult>
        <bndbox>
            <xmin>423</xmin>
            <ymin>124</ymin>
            <xmax>520</xmax>
            <ymax>214</ymax>
        </bndbox>
    </object>
    <object>
        <name>oiltank</name>
        <pose>Unspecified</pose>
        <truncated>0</truncated>
        <difficult>0</difficult>
        <bndbox>
            <xmin>423</xmin>
            <ymin>124</ymin>
            <xmax>520</xmax>
            <ymax>214</ymax>
        </bndbox>
    </object>
    <object>
        <name>oiltank</name>
        <pose>Unspecified</pose>
        <truncated>0</truncated>
        <difficult>0</difficult>
        <bndbox>
            <xmin>487</xmin>
            <ymin>181</ymin>
            <xmax>579</xmax>
            <ymax>278</ymax>
        </bndbox>
    </object>
    <object>
        <name>oiltank</name>
        <pose>Unspecified</pose>
        <truncated>0</truncated>
        <difficult>0</difficult>
        <bndbox>
            <xmin>399</xmin>
            <ymin>208</ymin>
            <xmax>495</xmax>
            <ymax>299</ymax>
        </bndbox>
    </object>
    <object>
        <name>oiltank</name>
        <pose>Unspecified</pose>
        <truncated>0</truncated>
        <difficult>0</difficult>
        <bndbox>
            <xmin>374</xmin>
            <ymin>290</ymin>
            <xmax>469</xmax>
            <ymax>385</ymax>
        </bndbox>
    </object>
    <object>
        <name>oiltank</name>
        <pose>Unspecified</pose>
        <truncated>0</truncated>
        <difficult>0</difficult>
        <bndbox>
            <xmin>350</xmin>
            <ymin>376</ymin>
            <xmax>444</xmax>
            <ymax>473</ymax>
        </bndbox>
    </object>
    <object>
        <name>oiltank</name>
        <pose>Unspecified</pose>
        <truncated>0</truncated>
        <difficult>0</difficult>
        <bndbox>
            <xmin>327</xmin>
            <ymin>458</ymin>
            <xmax>422</xmax>
            <ymax>560</ymax>
        </bndbox>
    </object>
    <object>
        <name>oiltank</name>
        <pose>Unspecified</pose>
        <truncated>0</truncated>
        <difficult>0</difficult>
        <bndbox>
            <xmin>303</xmin>
            <ymin>548</ymin>
            <xmax>399</xmax>
            <ymax>658</ymax>
        </bndbox>
    </object>
    <object>
        <name>oiltank</name>
        <pose>Unspecified</pose>
        <truncated>0</truncated>
        <difficult>0</difficult>
        <bndbox>
            <xmin>362</xmin>
            <ymin>611</ymin>
            <xmax>463</xmax>
            <ymax>727</ymax>
        </bndbox>
    </object>
    <object>
        <name>oiltank</name>
        <pose>Unspecified</pose>
        <truncated>0</truncated>
        <difficult>0</difficult>
        <bndbox>
            <xmin>393</xmin>
            <ymin>521</ymin>
            <xmax>490</xmax>
            <ymax>632</ymax>
        </bndbox>
    </object>
    <object>
        <name>oiltank</name>
        <pose>Unspecified</pose>
        <truncated>0</truncated>
        <difficult>0</difficult>
        <bndbox>
            <xmin>411</xmin>
            <ymin>436</ymin>
            <xmax>510</xmax>
            <ymax>538</ymax>
        </bndbox>
    </object>
    <object>
        <name>oiltank</name>
        <pose>Unspecified</pose>
        <truncated>0</truncated>
        <difficult>0</difficult>
        <bndbox>
            <xmin>440</xmin>
            <ymin>352</ymin>
            <xmax>538</xmax>
            <ymax>457</ymax>
        </bndbox>
    </object>
    <object>
        <name>oiltank</name>
        <pose>Unspecified</pose>
        <truncated>0</truncated>
        <difficult>0</difficult>
        <bndbox>
            <xmin>462</xmin>
            <ymin>263</ymin>
            <xmax>559</xmax>
            <ymax>364</ymax>
        </bndbox>
    </object>
</annotation>
