<annotation>
    <folder>VOC2007</folder>
    <filename>00000063.jpg</filename>
    <source>
        <database>My Database</database>
        <annotation>VOC2007</annotation>
        <image>flickr</image>
        <flickrid>NULL</flickrid>
    </source>
    <owner>
        <flickrid>NULL</flickrid>
        <name>LK</name>
    </owner>
    <size>
        <width>1044</width>
        <height>915</height>
        <depth>3</depth>
    </size>
    <segmented>0</segmented>
    <object>
        <name>aircraft</name>
        <pose>Unspecified</pose>
        <truncated>0</truncated>
        <difficult>0</difficult>
        <bndbox>
            <xmin>406</xmin>
            <ymin>574</ymin>
            <xmax>471</xmax>
            <ymax>627</ymax>
        </bndbox>
    </object>
    <object>
        <name>aircraft</name>
        <pose>Unspecified</pose>
        <truncated>0</truncated>
        <difficult>0</difficult>
        <bndbox>
            <xmin>406</xmin>
            <ymin>574</ymin>
            <xmax>471</xmax>
            <ymax>627</ymax>
        </bndbox>
    </object>
    <object>
        <name>aircraft</name>
        <pose>Unspecified</pose>
        <truncated>0</truncated>
        <difficult>0</difficult>
        <bndbox>
            <xmin>994</xmin>
            <ymin>154</ymin>
            <xmax>1041</xmax>
            <ymax>202</ymax>
        </bndbox>
    </object>
</annotation>
