<annotation>
    <folder>VOC2007</folder>
    <filename>00000607.jpg</filename>
    <source>
        <database>My Database</database>
        <annotation>VOC2007</annotation>
        <image>flickr</image>
        <flickrid>NULL</flickrid>
    </source>
    <owner>
        <flickrid>NULL</flickrid>
        <name>LK</name>
    </owner>
    <size>
        <width>589</width>
        <height>843</height>
        <depth>3</depth>
    </size>
    <segmented>0</segmented>
    <object>
        <name>oiltank</name>
        <pose>Unspecified</pose>
        <truncated>0</truncated>
        <difficult>0</difficult>
        <bndbox>
            <xmin>-119</xmin>
            <ymin>265</ymin>
            <xmax>10</xmax>
            <ymax>388</ymax>
        </bndbox>
    </object>
    <object>
        <name>oiltank</name>
        <pose>Unspecified</pose>
        <truncated>0</truncated>
        <difficult>0</difficult>
        <bndbox>
            <xmin>-119</xmin>
            <ymin>265</ymin>
            <xmax>10</xmax>
            <ymax>388</ymax>
        </bndbox>
    </object>
    <object>
        <name>oiltank</name>
        <pose>Unspecified</pose>
        <truncated>0</truncated>
        <difficult>0</difficult>
        <bndbox>
            <xmin>-114</xmin>
            <ymin>415</ymin>
            <xmax>13</xmax>
            <ymax>547</ymax>
        </bndbox>
    </object>
    <object>
        <name>oiltank</name>
        <pose>Unspecified</pose>
        <truncated>0</truncated>
        <difficult>0</difficult>
        <bndbox>
            <xmin>36</xmin>
            <ymin>252</ymin>
            <xmax>165</xmax>
            <ymax>387</ymax>
        </bndbox>
    </object>
    <object>
        <name>oiltank</name>
        <pose>Unspecified</pose>
        <truncated>0</truncated>
        <difficult>0</difficult>
        <bndbox>
            <xmin>42</xmin>
            <ymin>408</ymin>
            <xmax>172</xmax>
            <ymax>538</ymax>
        </bndbox>
    </object>
</annotation>
